trixellookupclient-0.2.0.dist-info/METADATA
trixellookupclient-0.2.0.dist-info/WHEEL
trixellookupclient-0.2.0.dist-info/licenses/LICENSE
trixellookupclient/__init__.py
trixellookupclient/api/__init__.py
trixellookupclient/api/default/__init__.py
trixellookupclient/api/default/ping_ping_get.py
trixellookupclient/api/default/version_version_get.py
trixellookupclient/api/trixel_information/__init__.py
trixellookupclient/api/trixel_information/batch_update_trixel_count_trixel_sensor_count_type_put.py
trixellookupclient/api/trixel_information/get_all_trixels_which_have_registered_sensors_trixel_get.py
trixellookupclient/api/trixel_information/get_sub_trixels_which_have_registered_sensors_trixel_trixel_id_get.py
trixellookupclient/api/trixel_information/get_tms_which_manages_the_trixel_trixel_trixel_id_tms_get.py
trixellookupclient/api/trixel_information/get_trixel_sensor_count_trixel_trixel_id_sensor_count_get.py
trixellookupclient/api/trixel_information/update_trixel_count_trixel_trixel_id_sensor_count_type_put.py
trixellookupclient/api/trixel_management_servers/__init__.py
trixellookupclient/api/trixel_management_servers/add_tms_tms_post.py
trixellookupclient/api/trixel_management_servers/get_all_delegations_for_the_provided_tms_tms_tms_id_delegations_get.py
trixellookupclient/api/trixel_management_servers/get_all_delegations_tms_delegations_get.py
trixellookupclient/api/trixel_management_servers/get_tms_i_ds_tms_get.py
trixellookupclient/api/trixel_management_servers/get_tms_info_tms_tms_id_get.py
trixellookupclient/api/trixel_management_servers/update_tms_details_tms_tms_id_put.py
trixellookupclient/api/trixel_management_servers/validate_tms_token_tms_tms_id_validate_token_get.py
trixellookupclient/client.py
trixellookupclient/errors.py
trixellookupclient/models/__init__.py
trixellookupclient/models/batch_update_trixel_count_trixel_sensor_count_type_put_updates.py
trixellookupclient/models/http_validation_error.py
trixellookupclient/models/measurement_type_enum.py
trixellookupclient/models/ping.py
trixellookupclient/models/tms_delegation.py
trixellookupclient/models/trixel_management_server.py
trixellookupclient-0.2.0.dist-info/RECORD
