Metadata-Version: 2.1
Name: trixellookupclient
Version: 0.2.0
Summary: A client module for accessing the Trixel Lookup Service (API)
Author-Email: Till <till@fleisch.dev>
License: # MIT License
Project-URL: Homepage, https://github.com/TillFleisch/TrixelLookupService
Project-URL: Repository, https://github.com/TillFleisch/TrixelLookupService.git
Project-URL: Issues, https://github.com/TillFleisch/TrixelLookupService/issues
Requires-Python: <4.0,>=3.8
Requires-Dist: httpx<0.28.0,>=0.20.0
Requires-Dist: attrs>=21.3.0
Requires-Dist: python-dateutil>=2.8.0
